{
  "Term Insurance Product Overview 215E.pdf": {
    "size": 904205,
    "last_modified": "2025-05-25T19:03:30+00:00",
    "chunks": 10,
    "indexed_at": "2025-05-25T20:03:12.252533"
  },
  "Term Life Product Overview 215E.pdf": {
    "size": 331713,
    "last_modified": "2025-05-25T19:03:33+00:00",
    "chunks": 11,
    "indexed_at": "2025-05-25T20:03:12.798691"
  },
  "Understanding Universal Life Insurance 339E.pdf": {
    "size": 1842573,
    "last_modified": "2025-05-25T19:03:38+00:00",
    "chunks": 24,
    "indexed_at": "2025-05-25T20:03:13.921747"
  },
  "accelerated-underwriting-faq-870e.pdf": {
    "size": 314790,
    "last_modified": "2025-05-25T19:03:06+00:00",
    "chunks": 12,
    "indexed_at": "2025-05-25T20:03:14.555331"
  },
  "bmo-insurance-whole-life-plan-advisor-guide-753E.pdf": {
    "size": 6748891,
    "last_modified": "2025-05-25T19:03:18+00:00",
    "chunks": 98,
    "indexed_at": "2025-05-25T20:03:18.216919"
  },
  "field-underwriting-manual-984e.pdf": {
    "size": 743680,
    "last_modified": "2025-05-25T19:03:25+00:00",
    "chunks": 127,
    "indexed_at": "2025-05-25T20:03:23.462341"
  },
  "quick-facts-514e.pdf": {
    "size": 300980,
    "last_modified": "2025-05-25T19:03:28+00:00",
    "chunks": 10,
    "indexed_at": "2025-05-25T20:03:24.028122"
  },
  "understanding_whole_life_insurance_344e.pdf": {
    "size": 1966586,
    "last_modified": "2025-05-25T19:03:43+00:00",
    "chunks": 13,
    "indexed_at": "2025-05-25T20:03:24.677614"
  }
}